kenshi_translator_toolkit/__init__.py
kenshi_translator_toolkit/version.py
kenshi_translator_toolkit/domain/__init__.py
kenshi_translator_toolkit/domain/entities/__init__.py
kenshi_translator_toolkit/domain/entities/data.py
kenshi_translator_toolkit/domain/entities/dialog.py
kenshi_translator_toolkit/domain/entities/record.py
kenshi_translator_toolkit/domain/entities/typecode.py
kenshi_translator_toolkit/infrastructure/__init__.py
kenshi_translator_toolkit/infrastructure/decoder/__init__.py
kenshi_translator_toolkit/infrastructure/decoder/decoder_helpers.py
kenshi_translator_toolkit/infrastructure/decoder/decoder_utils.py
kenshi_translator_toolkit/infrastructure/decoder/mod_decoder.py
kenshi_translator_toolkit/infrastructure/encoder/__init__.py
kenshi_translator_toolkit/infrastructure/encoder/encoder_helpers.py
kenshi_translator_toolkit/infrastructure/encoder/encoder_utils.py
kenshi_translator_toolkit/infrastructure/encoder/mod_encoder.py
kenshi_translator_toolkit-0.2.1.dist-info/licenses/LICENSE
kenshi_translator_toolkit-0.2.1.dist-info/METADATA
kenshi_translator_toolkit-0.2.1.dist-info/WHEEL
kenshi_translator_toolkit-0.2.1.dist-info/top_level.txt
kenshi_translator_toolkit-0.2.1.dist-info/RECORD
