Metadata-Version: 2.4
Name: kenshi-translator-toolkit
Version: 0.2.1
Summary: Ferramenta para extração e reinserção de textos em arquivos .mod do Kenshi (Beta)
Project-URL: Homepage, https://github.com/AlexPrestes/kenshi-translator-toolkit
Project-URL: Repository, https://github.com/AlexPrestes/kenshi-translator-toolkit
Project-URL: Documentation, https://github.com/AlexPrestes/kenshi-translator-toolkit/blob/main/README.md
Project-URL: Bug Tracker, https://github.com/AlexPrestes/kenshi-translator-toolkit/issues
Classifier: Development Status :: 4 - Beta
Classifier: Intended Audience :: Developers
Classifier: License :: OSI Approved :: MIT License
Classifier: Programming Language :: Python :: 3
Requires-Python: >=3.8
License-File: LICENSE
Dynamic: license-file
